hybridnn/__init__.py
hybridnn/activation.py
hybridnn/hybridnn.py
hybridnn/preprocessing.py
hybridnn-0.0.21.dist-info/LICENSE
hybridnn-0.0.21.dist-info/METADATA
hybridnn-0.0.21.dist-info/WHEEL
hybridnn-0.0.21.dist-info/top_level.txt
hybridnn-0.0.21.dist-info/RECORD
