Metadata-Version: 2.1
Name: hybridnn
Version: 0.0.21
Summary: Package for Backpropagation and Hybrid Neural Netwok with Particle Swarm Optimization
Author-email: Ahmad Zidni Zainul Ikhsan <zidnizainul03@gmail.com>
License: MIT License
Project-URL: Homepage, https://github.com/zidny-z/hybridnn
Project-URL: Issues, https://github.com/zidny-z/hybridnn/issues
Classifier: Programming Language :: Python :: 3
Classifier: License :: OSI Approved :: MIT License
Classifier: Operating System :: OS Independent
Requires-Python: >=3.8
License-File: LICENSE
Requires-Dist: numpy ==1.23.2
